odoo/addons/pos_access_right/README.rst
odoo/addons/pos_access_right/__init__.py
odoo/addons/pos_access_right/__manifest__.py
odoo/addons/pos_access_right/demo/res_groups.xml
odoo/addons/pos_access_right/i18n/ar.po
odoo/addons/pos_access_right/i18n/ca.po
odoo/addons/pos_access_right/i18n/es.po
odoo/addons/pos_access_right/i18n/fr.po
odoo/addons/pos_access_right/i18n/pos_access_right.pot
odoo/addons/pos_access_right/i18n/ru.po
odoo/addons/pos_access_right/models/__init__.py
odoo/addons/pos_access_right/models/pos_config.py
odoo/addons/pos_access_right/readme/CONFIGURE.rst
odoo/addons/pos_access_right/readme/CONTRIBUTORS.rst
odoo/addons/pos_access_right/readme/DESCRIPTION.rst
odoo/addons/pos_access_right/readme/USAGE.rst
odoo/addons/pos_access_right/security/res_groups.xml
odoo/addons/pos_access_right/static/description/admin_numpad.png
odoo/addons/pos_access_right/static/description/demo_error.png
odoo/addons/pos_access_right/static/description/demo_numpad.png
odoo/addons/pos_access_right/static/description/icon.png
odoo/addons/pos_access_right/static/description/index.html
odoo/addons/pos_access_right/static/description/new_groups.png
odoo/addons/pos_access_right/static/src/css/pos_access_right.css
odoo/addons/pos_access_right/static/src/js/pos_access_right.js
odoo/addons/pos_access_right/static/src/xml/templates.xml
odoo12_addon_pos_access_right-12.0.1.0.2.dist-info/METADATA
odoo12_addon_pos_access_right-12.0.1.0.2.dist-info/WHEEL
odoo12_addon_pos_access_right-12.0.1.0.2.dist-info/top_level.txt
odoo12_addon_pos_access_right-12.0.1.0.2.dist-info/RECORD
